gradient_cache/__init__.py
gradient_cache/core/__init__.py
gradient_cache/core/adaptive_compressor.py
gradient_cache/core/compressor.py
gradient_cache/core/hook_manager.py
gradient_cache/core/memory_manager.py
gradient_cache/integrations/__init__.py
gradient_cache/integrations/metaflow_decorator.py
gradient_cache-1.0.0.dist-info/licenses/LICENSE
gradient_cache-1.0.0.dist-info/METADATA
gradient_cache-1.0.0.dist-info/WHEEL
gradient_cache-1.0.0.dist-info/entry_points.txt
gradient_cache-1.0.0.dist-info/top_level.txt
gradient_cache-1.0.0.dist-info/RECORD
