Metadata-Version: 2.4
Name: gradient-cache
Version: 1.0.0
Summary: GPU memory-efficient training with gradient compression for PyTorch
Home-page: https://github.com/gradient-cache/gradient-cache
Author: Gradient Cache Contributors
Author-email: 
License: Apache License 2.0
Project-URL: Bug Tracker, https://github.com/gradient-cache/gradient-cache/issues
Project-URL: Documentation, https://github.com/gradient-cache/gradient-cache/wiki
Project-URL: Source Code, https://github.com/gradient-cache/gradient-cache
Keywords: deep learning,pytorch,gpu memory,gradient compression,machine learning,memory optimization,training efficiency,neural networks
Classifier: Development Status :: 4 - Beta
Classifier: Intended Audience :: Developers
Classifier: Intended Audience :: Science/Research
Classifier: Topic :: Scientific/Engineering :: Artificial Intelligence
Classifier: License :: OSI Approved :: Apache Software License
Classifier: Programming Language :: Python :: 3
Classifier: Programming Language :: Python :: 3.8
Classifier: Programming Language :: Python :: 3.9
Classifier: Programming Language :: Python :: 3.10
Classifier: Programming Language :: Python :: 3.11
Classifier: Operating System :: OS Independent
Classifier: Environment :: GPU :: NVIDIA CUDA
Requires-Python: >=3.8
License-File: LICENSE
Requires-Dist: torch>=2.0.0
Requires-Dist: numpy>=1.20.0
Requires-Dist: metaflow>=2.7.0
Provides-Extra: dev
Requires-Dist: pytest>=7.0.0; extra == "dev"
Requires-Dist: pytest-cov>=3.0.0; extra == "dev"
Requires-Dist: black>=22.0.0; extra == "dev"
Requires-Dist: isort>=5.0.0; extra == "dev"
Requires-Dist: flake8>=4.0.0; extra == "dev"
Requires-Dist: mypy>=0.950; extra == "dev"
Provides-Extra: benchmarks
Requires-Dist: transformers>=4.30.0; extra == "benchmarks"
Requires-Dist: psutil>=5.9.0; extra == "benchmarks"
Requires-Dist: gputil>=1.4.0; extra == "benchmarks"
Requires-Dist: matplotlib>=3.5.0; extra == "benchmarks"
Requires-Dist: pandas>=1.4.0; extra == "benchmarks"
Provides-Extra: docs
Requires-Dist: sphinx>=4.5.0; extra == "docs"
Requires-Dist: sphinx-rtd-theme>=1.0.0; extra == "docs"
Requires-Dist: myst-parser>=0.17.0; extra == "docs"
Dynamic: author
Dynamic: classifier
Dynamic: description
Dynamic: description-content-type
Dynamic: home-page
Dynamic: keywords
Dynamic: license
Dynamic: license-file
Dynamic: project-url
Dynamic: provides-extra
Dynamic: requires-dist
Dynamic: requires-python
Dynamic: summary
